{"height":11,"infinite":false,"layers":[{"id":14,"name":"camera","objects":[{"height":271,"id":12,"type":"frame","width":316,"x":50,"y":32},{"id":15,"type":"cameraStrategy","x":3,"y":126}],"type":"objectgroup","x":0,"y":0},{"id":2,"name":"objects","objects":[{"id":33,"properties":[{"name":"initialDirection","value":"s"}],"type":"hero","x":143,"y":86},{"id":34,"properties":[{"name":"initialDirection","value":"s"}],"type":"hero","x":174,"y":88},{"id":35,"properties":[{"name":"initialDirection","value":"s"}],"type":"hero","x":207,"y":84},{"id":36,"properties":[{"name":"initialDirection","value":"s"}],"type":"hero","x":240,"y":84},{"id":37,"properties":[{"name":"initialDirection","value":"s"}],"type":"hero","x":270,"y":86},{"id":38,"properties":[{"name":"initialDirection","value":"s"}],"type":"hero","x":304,"y":82},{"id":99,"type":"marker","x":111,"y":119},{"id":120,"type":"marker","x":146,"y":115}],"type":"objectgroup","x":0,"y":0},{"data":[79,79,79,79,79,79,79,79,79,79,79,79,79,79,70,70,70,70,70,70,70,70,70,70,70,79,79,70,80,80,80,80,80,80,80,80,80,70,79,79,70,80,80,80,80,80,80,80,80,80,70,79,79,70,80,80,80,80,80,80,80,80,80,70,79,79,70,80,80,80,80,80,80,80,80,80,70,79,79,70,80,80,80,80,80,80,80,80,80,70,79,79,70,80,80,80,80,80,80,80,80,80,70,79,79,70,80,80,80,80,80,80,80,80,80,70,79,79,70,70,70,70,70,70,70,70,70,70,70,79,79,79,79,79,79,79,79,79,79,79,79,79,79],"height":11,"id":282,"name":"types","type":"tilelayer","width":13,"x":0,"y":0},{"data":[0,0,0,0,0,0,0,0,0,0,0,0,0,0,1,2,5,4,2,5,5,4,5,2,6,0,0,11,8,142,8,154,30,152,37,121,30,16,0,0,21,154,37,154,38,144,28,131,27,153,16,0,0,11,27,144,17,134,30,144,10,132,7,26,0,0,21,142,29,123,40,143,19,153,37,151,26,0,0,21,28,132,20,154,28,123,9,124,39,26,0,0,11,154,7,154,20,123,38,124,30,132,16,0,0,31,9,153,20,124,38,133,38,132,20,36,0,0,41,42,52,43,52,53,43,42,53,45,46,0,0,0,0,0,0,0,0,0,0,0,0,0,0],"height":11,"id":283,"name":"ground","type":"tilelayer","width":13,"x":0,"y":0},{"data":[0,0,0,0,0,0,0,0,0,0,0,0,0,0,0,0,0,0,0,0,0,0,0,0,0,0,0,0,12,13,13,13,13,13,13,13,15,0,0,0,0,22,0,0,0,0,0,0,0,25,0,0,0,0,22,0,0,0,0,0,0,0,25,0,0,0,0,22,0,0,0,0,0,0,0,25,0,0,0,0,22,0,0,0,0,0,0,0,25,0,0,0,0,22,0,0,0,0,0,0,0,25,0,0,0,0,32,33,33,33,33,33,33,33,35,0,0,0,0,0,0,0,0,0,0,0,0,0,0,0,0,0,0,0,0,0,0,0,0,0,0,0,0],"height":11,"id":284,"name":"floor_shadow","type":"tilelayer","width":13,"x":0,"y":0}],"nextlayerid":285,"nextobjectid":121,"orientation":"orthogonal","renderorder":"right-down","tiledversion":"2019.03.13","tileheight":32,"tilesets":[{"columns":10,"firstgid":1,"image":"../maps/tileset.png","imageheight":680,"imagewidth":340,"margin":1,"name":"tileset","spacing":2,"terrains":[{"name":"floor","tile":79},{"name":"wall","tile":69},{"name":"hole","tile":78}],"tilecount":200,"tileheight":32,"tilewidth":32,"transparentcolor":"#000000"}],"tilewidth":32,"type":"map","version":1.2,"width":13}